common_functions/__init__.py
common_functions/constants.py
common_functions/edge_tools.py
common_functions/helpers.py
common_functions/logger.py
common_functions/models/__init__.py
common_functions/models/classification/__init__.py
common_functions/models/classification/keras_model_dense.py
common_functions/models/classification/keras_model_lstm.py
common_functions/models/classification/keras_model_phasedlstm.py
common_functions/models/estimation/__init__.py
common_functions/models/estimation/keras_model_conv1d.py
common_functions/models/estimation/keras_model_dense.py
common_functions/models/estimation/keras_model_lstm.py
common_functions/models/estimation/keras_model_phasedlstm.py
easierai_common_functions-1.9.2.dist-info/LICENSE
easierai_common_functions-1.9.2.dist-info/METADATA
easierai_common_functions-1.9.2.dist-info/WHEEL
easierai_common_functions-1.9.2.dist-info/top_level.txt
easierai_common_functions-1.9.2.dist-info/RECORD
