Metadata-Version: 2.1
Name: easierai-common-functions
Version: 1.9.2
Summary: This library contains reusable code for various projects
Home-page: https://scm.atosresearch.eu/ari/easier/common-python-helper-functions
Author: AIR Unit
Author-email: juan.carrascoa@atos.net
License: ATOS
Platform: UNKNOWN
Requires-Dist: schedule
Requires-Dist: joblib
Requires-Dist: pydash
Requires-Dist: tensorflow
Requires-Dist: phased-lstm-keras
Requires-Dist: scikit-learn
Requires-Dist: python-logstash
